{
  "product_slug": "brighthouse_shield_select_3",
  "product_name": "Shield Level Select 3",
  "carrier": "Brighthouse",
  "methodology_version": "v1.4.0",
  "product_spec_hash": "8a5cc01e17798a8a36cf952c18f41e878183fc1db1fd708adabf13348ee75a3f",
  "scored_at": "2026-05-13T00:00:00Z",
  "scoring_inputs": {
    "premium": 250000,
    "horizon_years": 30,
    "age": 60,
    "gender": "blend"
  },
  "monte_carlo": {
    "fees_pv_mean": 0.0,
    "me_fees_pv_mean": 0.0,
    "rider_fees_pv_mean": 0.0,
    "glwb_pv_mean": 0.0,
    "gmdb_pv_mean": 0.0,
    "av_end_p5": 118987.17,
    "av_end_p50": 295877.07,
    "av_end_p95": 665752.73,
    "av_paths_p50": [
      250000.0,
      262939.92,
      262579.9,
      261809.18,
      262790.13,
      263138.72,
      264395.31,
      265372.62,
      265489.54,
      266941.93,
      267948.87,
      269052.79,
      270620.97,
      273039.44,
      273421.6,
      275970.17,
      276909.27,
      278603.25,
      278251.08,
      281093.56,
      282125.79,
      283450.86,
      284870.7,
      286729.83,
      288979.55,
      290581.66,
      291436.62,
      292551.18,
      294164.16,
      295038.9,
      295877.07
    ]
  },
  "sub_scores": {
    "tco": {
      "score": 100.0,
      "rationale": "Annualised fee + cap-spread drag: 0.00%. Cohort best: 0.00%; cohort worst: 2.83%."
    },
    "gv": {
      "score": 100.0,
      "rationale": "Closed-form PV(buffer absorption) $22,458 with zero cost base \u2014 capped at 100."
    },
    "sf": {
      "score": 70.0,
      "rationale": "6-yr surrender schedule (max 7.0%); 10% free withdrawal; waivers: nursing-home, terminal-illness."
    },
    "ic": {
      "score": 83,
      "rationale": "AM Best A; not PE-owned; Level 3 assets 22%."
    },
    "bf": {
      "score": 90.0,
      "rationale": "0 major / 0 minor cap-rate cuts in 5yr; NAIC complaints index 0.50; 0 regulatory fines in 5yr."
    }
  },
  "composite": 88.6,
  "letter_grade": "A-",
  "allocation_scores": {
    "conservative": {
      "allocation_pcts": [
        1.0
      ],
      "sub_scores": {
        "tco": {
          "score": 100.0,
          "rationale": "Annualised fee + cap-spread drag: 0.00%. Cohort best: 0.00%; cohort worst: 2.83%."
        },
        "gv": {
          "score": 100.0,
          "rationale": "Closed-form PV(buffer absorption) $22,458 with zero cost base \u2014 capped at 100."
        },
        "sf": {
          "score": 70.0,
          "rationale": "6-yr surrender schedule (max 7.0%); 10% free withdrawal; waivers: nursing-home, terminal-illness."
        },
        "ic": {
          "score": 83,
          "rationale": "AM Best A; not PE-owned; Level 3 assets 22%."
        },
        "bf": {
          "score": 90.0,
          "rationale": "0 major / 0 minor cap-rate cuts in 5yr; NAIC complaints index 0.50; 0 regulatory fines in 5yr."
        }
      },
      "monte_carlo": {
        "fees_pv_mean": 0.0,
        "me_fees_pv_mean": 0.0,
        "rider_fees_pv_mean": 0.0,
        "glwb_pv_mean": 0.0,
        "gmdb_pv_mean": 0.0,
        "av_end_p5": 118987.17,
        "av_end_p50": 295877.07,
        "av_end_p95": 665752.73,
        "av_paths_p50": [
          250000.0,
          262939.92,
          262579.9,
          261809.18,
          262790.13,
          263138.72,
          264395.31,
          265372.62,
          265489.54,
          266941.93,
          267948.87,
          269052.79,
          270620.97,
          273039.44,
          273421.6,
          275970.17,
          276909.27,
          278603.25,
          278251.08,
          281093.56,
          282125.79,
          283450.86,
          284870.7,
          286729.83,
          288979.55,
          290581.66,
          291436.62,
          292551.18,
          294164.16,
          295038.9,
          295877.07
        ]
      },
      "composite": 88.6,
      "letter_grade": "A-"
    },
    "balanced": {
      "allocation_pcts": [
        1.0
      ],
      "sub_scores": {
        "tco": {
          "score": 100.0,
          "rationale": "Annualised fee + cap-spread drag: 0.00%. Cohort best: 0.00%; cohort worst: 2.83%."
        },
        "gv": {
          "score": 100.0,
          "rationale": "Closed-form PV(buffer absorption) $22,458 with zero cost base \u2014 capped at 100."
        },
        "sf": {
          "score": 70.0,
          "rationale": "6-yr surrender schedule (max 7.0%); 10% free withdrawal; waivers: nursing-home, terminal-illness."
        },
        "ic": {
          "score": 83,
          "rationale": "AM Best A; not PE-owned; Level 3 assets 22%."
        },
        "bf": {
          "score": 90.0,
          "rationale": "0 major / 0 minor cap-rate cuts in 5yr; NAIC complaints index 0.50; 0 regulatory fines in 5yr."
        }
      },
      "monte_carlo": {
        "fees_pv_mean": 0.0,
        "me_fees_pv_mean": 0.0,
        "rider_fees_pv_mean": 0.0,
        "glwb_pv_mean": 0.0,
        "gmdb_pv_mean": 0.0,
        "av_end_p5": 118987.17,
        "av_end_p50": 295877.07,
        "av_end_p95": 665752.73,
        "av_paths_p50": [
          250000.0,
          262939.92,
          262579.9,
          261809.18,
          262790.13,
          263138.72,
          264395.31,
          265372.62,
          265489.54,
          266941.93,
          267948.87,
          269052.79,
          270620.97,
          273039.44,
          273421.6,
          275970.17,
          276909.27,
          278603.25,
          278251.08,
          281093.56,
          282125.79,
          283450.86,
          284870.7,
          286729.83,
          288979.55,
          290581.66,
          291436.62,
          292551.18,
          294164.16,
          295038.9,
          295877.07
        ]
      },
      "composite": 88.6,
      "letter_grade": "A-"
    },
    "growth": {
      "allocation_pcts": [
        1.0
      ],
      "sub_scores": {
        "tco": {
          "score": 100.0,
          "rationale": "Annualised fee + cap-spread drag: 0.00%. Cohort best: 0.00%; cohort worst: 2.83%."
        },
        "gv": {
          "score": 100.0,
          "rationale": "Closed-form PV(buffer absorption) $22,458 with zero cost base \u2014 capped at 100."
        },
        "sf": {
          "score": 70.0,
          "rationale": "6-yr surrender schedule (max 7.0%); 10% free withdrawal; waivers: nursing-home, terminal-illness."
        },
        "ic": {
          "score": 83,
          "rationale": "AM Best A; not PE-owned; Level 3 assets 22%."
        },
        "bf": {
          "score": 90.0,
          "rationale": "0 major / 0 minor cap-rate cuts in 5yr; NAIC complaints index 0.50; 0 regulatory fines in 5yr."
        }
      },
      "monte_carlo": {
        "fees_pv_mean": 0.0,
        "me_fees_pv_mean": 0.0,
        "rider_fees_pv_mean": 0.0,
        "glwb_pv_mean": 0.0,
        "gmdb_pv_mean": 0.0,
        "av_end_p5": 118987.17,
        "av_end_p50": 295877.07,
        "av_end_p95": 665752.73,
        "av_paths_p50": [
          250000.0,
          262939.92,
          262579.9,
          261809.18,
          262790.13,
          263138.72,
          264395.31,
          265372.62,
          265489.54,
          266941.93,
          267948.87,
          269052.79,
          270620.97,
          273039.44,
          273421.6,
          275970.17,
          276909.27,
          278603.25,
          278251.08,
          281093.56,
          282125.79,
          283450.86,
          284870.7,
          286729.83,
          288979.55,
          290581.66,
          291436.62,
          292551.18,
          294164.16,
          295038.9,
          295877.07
        ]
      },
      "composite": 88.6,
      "letter_grade": "A-"
    }
  },
  "allocation_range": {
    "min_composite": 88.6,
    "max_composite": 88.6,
    "spread_points": 0.0
  },
  "published_profile": "balanced",
  "stress_score": 8.7,
  "stress_letter_grade": "F",
  "worst_regime_key": "lost_decade_2000_2009",
  "feature_snapshot": {
    "me_fee_annual": 0.0,
    "rider_fee_annual": 0.0,
    "rollup_rate": 0.0,
    "withdrawal_rate_65": 0.0,
    "surrender_years": 6,
    "surrender_max_pct": 0.07,
    "free_withdrawal_pct": 0.1,
    "waivers": [
      "nursing-home",
      "terminal-illness"
    ],
    "waiver_count": 2,
    "step_up": false,
    "has_glwb": false,
    "headline_cap": 0.25,
    "am_best": "A",
    "pe_owned": false,
    "level_3_pct_2024": 0.22,
    "cap_cut_count_5yr": 0,
    "product_type": "rila",
    "first_offered": "2022-01-01",
    "best_1yr_cap": null,
    "best_6yr_cap": null,
    "best_participation": null,
    "best_buffer": 0.1,
    "best_floor": null,
    "segment_count": 1
  },
  "regimes": {
    "bull_1985_1999": {
      "display_name": "Secular bull (1985-1999)",
      "start_month": "1985-02",
      "end_month": "2000-01",
      "years": 15,
      "av_end": 618116.38,
      "av_min": 250000.0,
      "fees_pv": 0.0,
      "glwb_pv": 0.0,
      "gmdb_pv": 0.0,
      "shortfall_probability": 0.0,
      "regime_score": 100.0,
      "history_truncated": false
    },
    "lost_decade_2000_2009": {
      "display_name": "Lost decade (2000-2009)",
      "start_month": "2000-01",
      "end_month": "2009-12",
      "years": 10,
      "av_end": 157557.34,
      "av_min": 146263.28,
      "fees_pv": 0.0,
      "glwb_pv": 0.0,
      "gmdb_pv": 0.0,
      "shortfall_probability": 0.0,
      "regime_score": 8.7,
      "history_truncated": false
    },
    "gfc_2008_2010": {
      "display_name": "GFC stress window (2008-2010)",
      "start_month": "2008-01",
      "end_month": "2010-12",
      "years": 3,
      "av_end": 188463.99,
      "av_min": 162413.34,
      "fees_pv": 0.0,
      "glwb_pv": 0.0,
      "gmdb_pv": 0.0,
      "shortfall_probability": 0.0,
      "regime_score": 16.9,
      "history_truncated": false
    },
    "post_gfc_bull_2010_2021": {
      "display_name": "Post-GFC bull (2010-2021)",
      "start_month": "2010-01",
      "end_month": "2021-12",
      "years": 12,
      "av_end": 474676.99,
      "av_min": 250000.0,
      "fees_pv": 0.0,
      "glwb_pv": 0.0,
      "gmdb_pv": 0.0,
      "shortfall_probability": 0.0,
      "regime_score": 93.2,
      "history_truncated": false
    },
    "rate_hike_2022_2024": {
      "display_name": "Rate-hike cycle (2022-2024)",
      "start_month": "2022-01",
      "end_month": "2024-12",
      "years": 3,
      "av_end": 243707.2,
      "av_min": 210020.49,
      "fees_pv": 0.0,
      "glwb_pv": 0.0,
      "gmdb_pv": 0.0,
      "shortfall_probability": 0.0,
      "regime_score": 31.7,
      "history_truncated": false
    }
  },
  "narrative": "Brighthouse's Shield Level Select 3 earns a composite score of 88.6, which maps to a letter grade of A- under AnnuityVoice Methodology v1.4.0. Relative strengths versus the cohort include Total Cost of Ownership (100), Guarantee Value (100), Insurer Credit (83), Behavioral Fairness (90). This rating reflects the standardized scoring scenario (60-year-old male, $250,000 premium, income election at 65, 30-year horizon, 7% / 18% equity drift / vol, 4% discount rate). Contract terms vary; consult the product prospectus and a qualified advisor before purchase.",
  "verdict": "Mostly solid; strongest in low fees (100), softest in restrictive surrender terms (70).",
  "signed_by": "K Hu",
  "signed_credentials": "FSA, MAAA",
  "signed_at": "2026-05-13T00:00:00Z",
  "status": "published"
}