{
  "product_slug": "prudential_flexguard_life",
  "product_name": "FlexGuard Life",
  "carrier": "Prudential",
  "methodology_version": "v1.2.0",
  "product_spec_hash": "bb2fbfadae395649f510dde70c082760fdecfa75d155bb54696d77c8aff53b95",
  "scored_at": "2026-05-12T00:00:00Z",
  "scoring_inputs": {
    "premium": 250000,
    "horizon_years": 30,
    "age": 60,
    "gender": "blend",
    "gender_blend": true,
    "genders_blended": [
      "M",
      "F"
    ]
  },
  "monte_carlo": {
    "fees_pv_mean": 38519.39,
    "glwb_pv_mean": 0.0,
    "gmdb_pv_mean": 0.0,
    "av_end_p5": 138890.27,
    "av_end_p50": 294879.28,
    "av_end_p95": 583379.8
  },
  "monte_carlo_male": {
    "fees_pv_mean": 37669.87,
    "glwb_pv_mean": 0.0,
    "gmdb_pv_mean": 0.0,
    "av_end_p5": 138890.27,
    "av_end_p50": 294879.28,
    "av_end_p95": 583379.8
  },
  "monte_carlo_female": {
    "fees_pv_mean": 39368.9,
    "glwb_pv_mean": 0.0,
    "gmdb_pv_mean": 0.0,
    "av_end_p5": 138890.27,
    "av_end_p50": 294879.28,
    "av_end_p95": 583379.8
  },
  "sub_scores": {
    "tco": {
      "score": 55.8,
      "rationale": "Annualised fee + cap-spread drag: 1.25%. Cohort best: 0.00%; cohort worst: 2.83%."
    },
    "gv": {
      "score": 63.3,
      "rationale": "PV(buffer+floor absorption) / PV(M&E+cap-drag) = 1.27x. Buffer PV $69,080; floor PV $0; cost-base PV $54,594. Closed-form lognormal (\u03bc=7.00%, \u03c3=18.00%, r=4.00%). (male) / PV(buffer+floor absorption) / PV(M&E+cap-drag) = 1.27x. Buffer PV $69,080; floor PV $0; cost-base PV $54,594. Closed-form lognormal (\u03bc=7.00%, \u03c3=18.00%, r=4.00%). (female)"
    },
    "sf": {
      "score": 80.0,
      "rationale": "6-yr surrender schedule (max 6.0%); 10% free withdrawal; waivers: nursing-home, terminal-illness, disability."
    },
    "ic": {
      "score": 90.0,
      "rationale": "AM Best A+; not PE-owned; Level 3 assets 17%."
    },
    "bf": {
      "score": 90.0,
      "rationale": "0 major / 0 minor cap-rate cuts in 5yr; NAIC complaints index 0.50; 0 regulatory fines in 5yr."
    }
  },
  "male_scores": {
    "tco": {
      "score": 55.8,
      "rationale": "Annualised fee + cap-spread drag: 1.25%. Cohort best: 0.00%; cohort worst: 2.83%."
    },
    "gv": {
      "score": 63.3,
      "rationale": "PV(buffer+floor absorption) / PV(M&E+cap-drag) = 1.27x. Buffer PV $69,080; floor PV $0; cost-base PV $54,594. Closed-form lognormal (\u03bc=7.00%, \u03c3=18.00%, r=4.00%)."
    },
    "sf": {
      "score": 80.0,
      "rationale": "6-yr surrender schedule (max 6.0%); 10% free withdrawal; waivers: nursing-home, terminal-illness, disability."
    },
    "ic": {
      "score": 90,
      "rationale": "AM Best A+; not PE-owned; Level 3 assets 17%."
    },
    "bf": {
      "score": 90.0,
      "rationale": "0 major / 0 minor cap-rate cuts in 5yr; NAIC complaints index 0.50; 0 regulatory fines in 5yr."
    }
  },
  "female_scores": {
    "tco": {
      "score": 55.8,
      "rationale": "Annualised fee + cap-spread drag: 1.25%. Cohort best: 0.00%; cohort worst: 2.83%."
    },
    "gv": {
      "score": 63.3,
      "rationale": "PV(buffer+floor absorption) / PV(M&E+cap-drag) = 1.27x. Buffer PV $69,080; floor PV $0; cost-base PV $54,594. Closed-form lognormal (\u03bc=7.00%, \u03c3=18.00%, r=4.00%)."
    },
    "sf": {
      "score": 80.0,
      "rationale": "6-yr surrender schedule (max 6.0%); 10% free withdrawal; waivers: nursing-home, terminal-illness, disability."
    },
    "ic": {
      "score": 90,
      "rationale": "AM Best A+; not PE-owned; Level 3 assets 17%."
    },
    "bf": {
      "score": 90.0,
      "rationale": "0 major / 0 minor cap-rate cuts in 5yr; NAIC complaints index 0.50; 0 regulatory fines in 5yr."
    }
  },
  "blended_scores": {
    "tco": {
      "score": 55.8,
      "rationale": "Annualised fee + cap-spread drag: 1.25%. Cohort best: 0.00%; cohort worst: 2.83%."
    },
    "gv": {
      "score": 63.3,
      "rationale": "PV(buffer+floor absorption) / PV(M&E+cap-drag) = 1.27x. Buffer PV $69,080; floor PV $0; cost-base PV $54,594. Closed-form lognormal (\u03bc=7.00%, \u03c3=18.00%, r=4.00%). (male) / PV(buffer+floor absorption) / PV(M&E+cap-drag) = 1.27x. Buffer PV $69,080; floor PV $0; cost-base PV $54,594. Closed-form lognormal (\u03bc=7.00%, \u03c3=18.00%, r=4.00%). (female)"
    },
    "sf": {
      "score": 80.0,
      "rationale": "6-yr surrender schedule (max 6.0%); 10% free withdrawal; waivers: nursing-home, terminal-illness, disability."
    },
    "ic": {
      "score": 90.0,
      "rationale": "AM Best A+; not PE-owned; Level 3 assets 17%."
    },
    "bf": {
      "score": 90.0,
      "rationale": "0 major / 0 minor cap-rate cuts in 5yr; NAIC complaints index 0.50; 0 regulatory fines in 5yr."
    }
  },
  "male_composite": 75.8,
  "female_composite": 75.8,
  "male_letter_grade": "B",
  "female_letter_grade": "B",
  "composite": 75.8,
  "letter_grade": "B",
  "feature_snapshot": {
    "me_fee_annual": 0.0125,
    "rider_fee_annual": 0.0,
    "rollup_rate": 0.0,
    "withdrawal_rate_65": 0.0,
    "surrender_years": 6,
    "surrender_max_pct": 0.06,
    "free_withdrawal_pct": 0.1,
    "waivers": [
      "nursing-home",
      "terminal-illness",
      "disability"
    ],
    "waiver_count": 3,
    "step_up": false,
    "has_glwb": false,
    "headline_cap": 0.09,
    "am_best": "A+",
    "pe_owned": false,
    "level_3_pct_2024": 0.17,
    "cap_cut_count_5yr": 0,
    "product_type": "rila",
    "first_offered": "2022-01-01"
  },
  "regimes": {
    "bull_1985_1999": {
      "display_name": "Secular bull (1985-1999)",
      "start_month": "1985-02",
      "end_month": "2000-01",
      "years": 15,
      "av_end": 549710.12,
      "av_min": 250000.0,
      "fees_pv": 49244.0,
      "glwb_pv": 0.0,
      "gmdb_pv": 0.0,
      "shortfall_probability": 0.0,
      "regime_score": 100.0,
      "history_truncated": false
    },
    "lost_decade_2000_2009": {
      "display_name": "Lost decade (2000-2009)",
      "start_month": "2000-01",
      "end_month": "2009-12",
      "years": 10,
      "av_end": 165985.31,
      "av_min": 155024.1,
      "fees_pv": 20440.68,
      "glwb_pv": 0.0,
      "gmdb_pv": 0.0,
      "shortfall_probability": 0.0,
      "regime_score": 10.9,
      "history_truncated": false
    },
    "gfc_2008_2010": {
      "display_name": "GFC stress window (2008-2010)",
      "start_month": "2008-01",
      "end_month": "2010-12",
      "years": 3,
      "av_end": 191689.22,
      "av_min": 167505.73,
      "fees_pv": 6246.43,
      "glwb_pv": 0.0,
      "gmdb_pv": 0.0,
      "shortfall_probability": 0.0,
      "regime_score": 17.8,
      "history_truncated": false
    },
    "post_gfc_bull_2010_2021": {
      "display_name": "Post-GFC bull (2010-2021)",
      "start_month": "2010-01",
      "end_month": "2021-12",
      "years": 12,
      "av_end": 433476.58,
      "av_min": 250000.0,
      "fees_pv": 37924.04,
      "glwb_pv": 0.0,
      "gmdb_pv": 0.0,
      "shortfall_probability": 0.0,
      "regime_score": 82.3,
      "history_truncated": false
    },
    "rate_hike_2022_2024": {
      "display_name": "Rate-hike cycle (2022-2024)",
      "start_month": "2022-01",
      "end_month": "2024-12",
      "years": 3,
      "av_end": 245450.48,
      "av_min": 214517.79,
      "fees_pv": 7998.92,
      "glwb_pv": 0.0,
      "gmdb_pv": 0.0,
      "shortfall_probability": 0.0,
      "regime_score": 32.1,
      "history_truncated": false
    }
  },
  "narrative": "Prudential's FlexGuard Life earns a composite score of 75.8, which maps to a letter grade of B under AnnuityVoice Methodology v1.0.0. Relative strengths versus the cohort include Surrender Flexibility (80), Insurer Credit (90), Behavioral Fairness (90). Areas where this product scores below cohort median: Total Cost of Ownership (56). This rating reflects the standardized scoring scenario (60-year-old male, $250,000 premium, income election at 65, 30-year horizon, 7% / 18% equity drift / vol, 4% discount rate). Contract terms vary; consult the product prospectus and a qualified advisor before purchase.",
  "verdict": "Strong insurer credit (90) offset by high fee drag (56).",
  "signed_by": "K Hu",
  "signed_credentials": "FSA, MAAA",
  "signed_at": "2026-05-12T00:00:00Z",
  "status": "published"
}